{
  "id": "intro",
  "title": "Dokümantasyon Ana Sayfası",
  "description": "MHM Rentiva Araç Kiralama Eklentisi'nin kapsamlı dokümantasyonuna hoş geldiniz. Başlamak için aşağıdaki kategorilerden birini seçin.",
  "source": "@site/docs/intro.md",
  "sourceDirName": ".",
  "slug": "/",
  "permalink": "/mhm-rentiva-docs/en/docs/next/",
  "draft": false,
  "unlisted": false,
  "editUrl": "https://github.com/MaxHandMade/mhm-rentiva/tree/main/website/docs/intro.md",
  "tags": [],
  "version": "current",
  "sidebarPosition": 0,
  "frontMatter": {
    "slug": "/",
    "sidebar_position": 0,
    "title": "Dokümantasyon Ana Sayfası",
    "hide_table_of_contents": true
  },
  "sidebar": "tutorialSidebar",
  "next": {
    "title": "Başlangıç Rehberi",
    "permalink": "/mhm-rentiva-docs/en/docs/next/category/başlangıç-rehberi"
  }
}